tattl/__init__.py
tattl/_version.py
tattl/exceptions.py
tattl/py.typed
tattl/unpack.py
tattl-0.5.0.dist-info/METADATA
tattl-0.5.0.dist-info/WHEEL
tattl-0.5.0.dist-info/licenses/LICENSE
tattl-0.5.0.dist-info/RECORD
