Metadata-Version: 2.4
Name: tattl
Version: 0.5.0
Summary: Totally Awesome Type-aware TOML Loader
Project-URL: Source, https://github.com/thcrt/tattl
Project-URL: Issues, https://github.com/thcrt/tattl/issues
Project-URL: PyPI, https://pypi.org/project/tattl/
Author-email: thcrt <110127860+thcrt@users.noreply.github.com>
License: BSD 3-Clause License
License-File: LICENSE
Keywords: config,configuration,dataclass,settings,toml,typing,validation,yaml
Classifier: Development Status :: 4 - Beta
Classifier: Intended Audience :: Developers
Classifier: License :: OSI Approved :: BSD License
Classifier: Operating System :: OS Independent
Classifier: Programming Language :: Python :: 3
Classifier: Programming Language :: Python :: 3.12
Classifier: Topic :: File Formats
Classifier: Topic :: Software Development :: Libraries
Classifier: Topic :: Software Development :: Libraries :: Python Modules
Classifier: Topic :: Text Processing
Classifier: Typing :: Typed
Requires-Python: >=3.12
